Workbook
Name Slicer_ProductLine1: #N/A
Name Slicer_Region2: #N/A
Name Slicer_Helper4: #N/A
Name Slicer_ProductLine6: #N/A
Name Slicer_ProductLine7: #N/A
Name Slicer_Region8: #N/A
Name Slicer_Helper9: #N/A
Name Slicer_ProductLine: #N/A
Name Slicer_Helper: #N/A
Name Slicer_UnitsSold: #N/A
Name Slicer_Region: #N/A

Sheet Raw_data
A1: Date | B1: OrderID | C1: ProductID | D1: ProductLine | E1: Region | F1: UnitsSold | G1: UnitPrice | H1: UnitCost | I1: MarketingSpend
A2: 45619 | B2: 1001 | C2: P008 | D2: Gadgets | E2: North | F2: 1 | G2: 15.22 | H2: 8.03 | I2: 5.31
A3: 45624 | B3: 1002 | C3: P015 | D3: Tools | E3: South | F3: 10 | G3: 42.01 | H3: 27.04 | I3: 20.44
A4: 45475 | B4: 1003 | C4: P026 | D4: Widgets | E4: West | F4: 9 | G4: 101.58 | H4: 69.86 | I4: 115.47
A5: 45315 | B5: 1004 | C5: P003 | D5: Gadgets | E5: West | F5: 11 | G5: 29.57 | H5: 17.79 | I5: 140.36
A6: 45328 | B6: 1005 | C6: P024 | D6: Gadgets | E6: South | F6: 24 | G6: 95.81 | H6: 30.13 | I6: 63.09
A7: 45400 | B7: 1006 | C7: P023 | D7: Tools | E7: West | F7: 4 | G7: 38.64 | H7: 16.16 | I7: 116.92
A8: 45496 | B8: 1007 | C8: P005 | D8: Accessories | E8: North | F8: 5 | G8: 97.54 | H8: 32.05 | I8: 76.32
A9: 45562 | B9: 1008 | C9: P001 | D9: Widgets | E9: East | F9: 10 | G9: 24.05 | H9: 12.13 | I9: 190.76
A10: 45426 | B10: 1009 | C10: P017 | D10: Widgets | E10: South | F10: 24 | G10: 29.45 | H10: 21.06 | I10: 183.7
A11: 45542 | B11: 1010 | C11: P029 | D11: Tools | E11: North | F11: 15 | G11: 100.13 | H11: 54.04 | I11: 25.15
A12: 45573 | B12: 1011 | C12: P020 | D12: Accessories | E12: South | F12: 12 | G12: 119.48 | H12: 59.4 | I12: 103.52
A13: 45407 | B13: 1012 | C13: P018 | D13: Gadgets | E13: North | F13: 1 | G13: 104.84 | H13: 42.68 | I13: 133.8
... A15: 45626 | B15: 1014 | C15: P013 | D15: Tools | E15: South | F15: 14 | G15: 27.14 | H15: 13.79 | I15: 174.9
A16: 45491
A17: 45317 | B17: 1015 | C17: P018 | D17: Widgets | E17: South | F17: 15 | G17: 63.99 | H17: 45.18 | I17: 32.93
A18: 45596 | B18: 1016 | C18: P015 | D18: Tools | E18: West | F18: 9 | G18: 35.51 | H18: 22.41 | I18: 12.19
A19: 45296 | B19: 1017 | C19: P028 | D19: Gadgets | E19: South | F19: 2 | G19: 84.92 | H19: 30.06 | I19: 178.06
A20: 45605 | B20: 1018 | C20: P022 | D20: Tools | E20: East | F20: 12 | G20: 26.13 | H20: 13.22 | I20: 185.8
A21: 45399 | B21: 1019 | C21: P004 | D21: Widgets | E21: South | F21: 2 | G21: 106.96 | H21: 39.68 | I21: 166.75
A22: 45374 | B22: 1020 | C22: P017 | D22: Widgets | E22: North | F22: 4 | G22: 40.56 | H22: 25.72 | I22: 31.09
A23: 45312 | B23: 1021 | C23: P021 | D23: Tools | E23: North | F23: 13 | G23: 101.57 | H23: 45.72 | I23: 26.16
A24: 45503 | B24: 1022 | C24: P014 | D24: Widgets | E24: South | F24: 11 | G24: 74.91 | H24: 26.77 | I24: 61.65
A25: 45527 | B25: 1023 | C25: P008 | D25: Widgets | E25: West | F25: 23 | G25: 28.69 | H25: 19.77 | I25: 195.24
A26: 45566 | B26: 1024 | C26: P011 | D26: Accessories | E26: South | F26: 25 | G26: 87.74 | H26: 27.85 | I26: 94.14
A27: 45489 | B27: 1025 | C27: P028 | D27: Gadgets | E27: West | F27: 2 | G27: 116.42 | H27: 68.53 | I27: 79.94
A28: 45445 | B28: 1026 | C28: P029 | D28: Tools | E28: East | F28: 19 | G28: 58.93 | H28: 26 | I28: 121.24
... A50: 45522 | B50: 1048 | C50: P005 | D50: Tools | E50: West | F50: 25 | G50: 78.79 | H50: 37.12 | I50: 181.7
A51: 45509
A52: 45498 | B52: 1049 | C52: P020 | D52: Widgets | E52: South | F52: 8 | G52: 83.33 | H52: 31.52 | I52: 15.01
A53: 45501 | B53: 1050 | C53: P002 | D53: Gadgets | E53: West | F53: 7 | G53: 111.78 | H53: 64.98 | I53: 132.24
A54: 45516 | B54: 1051 | C54: P005 | D54: Tools | E54: South | F54: 19 | G54: 92.89 | H54: 39.93 | I54: 24.87
A55: 45370 | B55: 1052 | C55: P016 | D55: Accessories | E55: West | F55: 19 | G55: 39.04 | H55: 28.61 | I55: 167.19
A56: 45327 | B56: 1053 | C56: P009 | D56: Widgets | E56: West | F56: 5 | G56: 119.67 | H56: 79.75 | I56: 193.81
A57: 45487 | B57: 1054 | C57: P028 | D57: Gadgets | E57: East | F57: 12 | G57: 99.87 | H57: 50.4 | I57: 62.9
A58: 45371 | B58: 1055 | C58: P001 | D58: Accessories | E58: East | F58: 15 | G58: 79.54 | H58: 31.15 | I58: 109.84
A59: 45569 | B59: 1056 | C59: P001 | D59: Gadgets | E59: North | F59: 2 | G59: 36.27 | H59: 12.73 | I59: 189.41
A60: 45546 | B60: 1057 | C60: P017 | D60: Tools | E60: West | F60: 17 | G60: 27.62 | H60: 15.74 | I60: 149.26
A61: 45494 | B61: 1058 | C61: P014 | D61: Tools | E61: North | F61: 9 | G61: 102.45 | H61: 61.16 | I61: 173.05
A62: 45629 | B62: 1059 | C62: P018 | D62: Accessories | E62: South | F62: 7 | G62: 73.75 | H62: 47.86 | I62: 8.73
A63: 45479 | B63: 1060 | C63: P027 | D63: Gadgets | E63: East | F63: 14 | G63: 22.77 | H63: 6.99 | I63: 28.83
... A87: 45611 | B87: 1084 | C87: P002 | D87: Gadgets | E87: North | F87: 6 | G87: 94.87 | H87: 40.82 | I87: 24
A88: 45532 | B88: 1085 | C88: P023 | D88: Gadgets | E88: East | F88: 23 | G88: 16.57 | I88: 184.23
A89: 45620 | B89: 1086 | C89: P021 | D89: Accessories | E89: East | F89: 19 | G89: 61.69 | H89: 28.55 | I89: 87.34
A90: 45405 | B90: 1087 | C90: P013 | D90: Tools | E90: South | F90: 20 | G90: 24.31 | H90: 17.2 | I90: 69.88
A91: 45368 | B91: 1088 | C91: P005 | D91: Tools | E91: North | F91: 24 | G91: 79.82 | H91: 44.19 | I91: 115.89
A92: 45597 | B92: 1089 | C92: P011 | D92: Tools | E92: West | F92: 25 | G92: 41.66 | H92: 22.01 | I92: 62.08
A93: 45561 | B93: 1090 | C93: P021 | D93: Widgets | E93: West | F93: 25 | G93: 91.8 | H93: 65.09 | I93: 114.33
A94: 45345 | B94: 1091 | C94: P002 | D94: Accessories | E94: East | F94: 2 | G94: 66.49 | H94: 27.36 | I94: 87.55
A95: 45526 | B95: 1092 | C95: P030 | D95: Tools | E95: North | F95: 20 | G95: 48.14 | H95: 26.53 | I95: 77.31
A96: 45316 | B96: 1093 | C96: P005 | D96: Tools | E96: East | F96: 20 | G96: 87.44 | H96: 49.65 | I96: 187.6
A97: 45428 | B97: 1094 | C97: P005 | D97: Widgets | E97: East | F97: 9 | G97: 31.47 | H97: 22.86 | I97: 97.25
A98: 45519 | B98: 1095 | C98: P026 | D98: Widgets | E98: North | F98: 24 | G98: 78.75 | H98: 29.09 | I98: 36.17
A99: 45603 | B99: 1096 | C99: P015 | D99: Widgets | E99: South | F99: 19 | G99: 42.77 | H99: 21.47 | I99: 106.8
A100: 45331 | B100: 1097 | C100: P022 | D100: Accessories | E100: West | F100: 13 | G100: 116.36 | H100: 76.86 | I100: 27.68
A101: 45520 | B101: 1098 | C101: P030 | D101: Widgets | E101: North | F101: 24 | G101: 29.31 | H101: 15.56 | I101: 166.21
A102: 45469 | B102: 1099 | C102: P030 | D102: Widgets | E102: East | F102: 2 | G102: 52.49 | I102: 186.17
A103: 45476 | B103: 1100 | C103: P002 | D103: Tools | E103: South | F103: 15 | G103: 60.45 | I103: 15.85
A104: 45454 | B104: 1101 | C104: P017 | D104: Accessories | E104: East | F104: 7 | G104: 57.34 | H104: 29 | I104: 22.17
A105: 45376 | B105: 1102 | C105: P019 | D105: Gadgets | E105: North | F105: 7 | G105: 73.63 | H105: 44.23 | I105: 104.7
A106: 45339 | B106: 1103 | C106: P017 | D106: Widgets | E106: West | F106: 8 | G106: 92.71 | H106: 30.63 | I106: 48.23
A107: 45427 | B107: 1104 | C107: P011 | D107: gadgets | E107: South | F107: 21 | G107: 62.18 | H107: 36.33 | I107: 162.3
A108: 45322 | B108: 1105 | C108: P026 | D108: Gadgets | E108: East | F108: 17 | G108: 63.13 | I108: 129.38
A109: 45530 | B109: 1106 | C109: P004 | D109: Tools | E109: West | F109: 12 | G109: 48.62 | H109: 29.73 | I109: 73.47
A110: 45555 | B110: 1107 | C110: P003 | D110: Accessories | E110: East | F110: 2 | G110: 47.42 | H110: 23.74 | I110: 143.53
A111: 45551 | B111: 1108 | C111: P028 | D111: Tools | E111: North | F111: 20 | G111: 55.87 | H111: 35.61 | I111: 32
A112: 45348 | B112: 1109 | C112: P005 | D112: Widgets | E112: East | F112: 18 | G112: 15.5 | H112: 7.79 | I112: 74.19
A113: 45536 | B113: 1110 | C113: P013 | D113: Tools | E113: North | F113: 5 | G113: 65.9 | H113: 36.43 | I113: 52.36
A114: 45434 | B114: 1111 | C114: P023 | D114: Accessories | E114: North | F114: 22 | G114: 60.07 | H114: 36.45 | I114: 169.1
A115: 45570 | B115: 1112 | C115: P010 | D115: Tools | E115: South | F115: 16 | G115: 36.22 | H115: 23.78 | I115: 47.35
A116: 45567 | B116: 1113 | C116: P026 | D116: Gadgets | E116: East | F116: 22 | G116: 89.64 | H116: 57.92 | I116: 164.67
A117: 45533 | B117: 1114 | C117: P022 | D117: Tools | E117: South | F117: 4 | G117: 58.72 | H117: 19.08 | I117: 24.83
A118: 45625 | B118: 1115 | C118: P008 | D118: Tools | E118: East | F118: 8 | G118: 33.2 | H118: 14.06 | I118: 125
A119: 45349 | B119: 1116 | C119: P019 | D119: Gadgets | E119: East | F119: 18 | G119: 16.45 | H119: 5.54 | I119: 189.71
A120: 45510 | B120: 1117 | C120: P014 | D120: Widgets | E120: East | F120: 9 | G120: 64.16 | H120: 39.03 | I120: 59.49
... A145: 45488 | B145: 1142 | C145: P008 | D145: Widgets | E145: West | F145: 17 | G145: 57.81 | H145: 23.32 | I145: 92.13
A146: 45439 | B146: 1143 | C146: P004 | D146: Widgets | E146: North | F146: 2 | G146: 22.9 | I146: 119.56
A147: 45571 | B147: 1144 | C147: P015 | D147: Gadgets | E147: North | F147: 9 | G147: 37.29 | H147: 20.85 | I147: 115.49
A148: 45441 | B148: 1145 | C148: P022 | D148: Gadgets | E148: South | F148: 13 | G148: 72.03 | H148: 32.77 | I148: 128.66
A149: 45480 | B149: 1146 | C149: P005 | D149: Tools | E149: West | F149: 7 | G149: 44.48 | H149: 29.47 | I149: 182.95
A150: 45511 | B150: 1147 | C150: P008 | D150: Tools | E150: West | F150: 2 | G150: 69.85 | H150: 22.57 | I150: 75.43
A151: 45360 | B151: 1148 | C151: P025 | D151: Gadgets | E151: East | F151: 0 | G151: 34.88 | H151: 22.1 | I151: 149.38
A152: 45343 | B152: 1149 | C152: P013 | D152: Gadgets | E152: West | F152: 20 | G152: 50.8 | H152: 26.96 | I152: 99.46
A153: 45305 | B153: 1150 | C153: P007 | D153: Tools | E153: South | F153: 0 | G153: 40.16 | H153: 22.51 | I153: 83.52
A154: 45299 | B154: 1151 | C154: P008 | D154: Accessories | E154: East | F154: 15 | G154: 116.38 | H154: 60.61 | I154: 33.65
A155: 45553 | B155: 1152 | C155: P006 | D155: Widgets | E155: North | F155: 21 | G155: 17.24 | I155: 27.5
A156: 45524 | B156: 1153 | C156: P017 | D156: Accessories | E156: West | F156: 0 | G156: 12.71 | H156: 3.88 | I156: 105.88
A157: 45429 | B157: 1154 | C157: P022 | D157: Accessories | E157: North | F157: 16 | G157: 28.08 | H157: 15.08 | I157: 163.04
A158: 45377 | B158: 1155 | C158: P015 | D158: Gadgets | E158: North | F158: 20 | G158: 94.04 | H158: 44.26 | I158: 110.54
A159: 45310 | B159: 1156 | C159: P028 | D159: Accessories | E159: North | F159: 1 | G159: 36.81 | H159: 22.51 | I159: 113.36
A160: 45556 | B160: 1157 | C160: P018 | D160: Widgets | E160: North | F160: 18 | G160: 27.57 | H160: 18.46 | I160: 185.77
A161: 45558 | B161: 1158 | C161: P013 | D161: Tools | E161: North | F161: 11 | G161: 17.8 | H161: 12.06 | I161: 68.12
A162: 45493 | B162: 1159 | C162: P001 | D162: Tools | E162: South | F162: 12 | G162: 58.64 | H162: 35.03 | I162: 17.14
A163: 45367 | B163: 1160 | C163: P005 | D163: Accessories | E163: West | F163: 3 | G163: 21.88 | H163: 10.94 | I163: 152.27
A164: 45528 | B164: 1161 | C164: P018 | D164: Accessories | E164: North | F164: 25 | G164: 47.04 | H164: 20.29 | I164: 77.56
A165: 45606 | B165: 1162 | C165: P019 | D165: Gadgets | E165: East | F165: 15 | G165: 27.76 | H165: 11.78 | I165: 59.95
A166: 45582 | B166: 1163 | C166: P021 | D166: Accessories | E166: North | F166: 0 | G166: 114.47 | H166: 66.29 | I166: 160.82
A167: 45514 | B167: 1164 | C167: P021 | D167: Gadgets | E167: South | F167: 5 | G167: 116.17 | H167: 50.09 | I167: 138.99
... A187: 45552 | B187: 1184 | C187: P014 | D187: Gadgets | E187: East | F187: 8 | G187: 22.08 | H187: 7.44 | I187: 132.9
A188: 45419
...

Sheet Data_Cleaned
A1: date_iso | B1: Date | C1: OrderID | D1: ProductID | E1: ProductLine | F1: Region | G1: UnitsSold | H1: UnitPrice | I1: UnitCost | J1: MarketingSpend | K1: Revenue | L1: COGS | M1: Gross_profit | N1: Margin% | O1: Helper
A2: 45619 | B2: 45619 | C2: 1001 | D2: P008 | E2: Gadgets | F2: North | G2: 1 | H2: 15.22 | I2: 8.03 | J2: 5.31 | K2: =G2*H2 -> 15.22 | L2: =I2*G2 -> 8.03 | M2: =K2-L2 -> 7.19 | N2: =M2/K2*100 -> 47.240473 | O2: =TEXT(A2,"YYYY-MM") -> 2024-11
A3: 45624 | B3: 45624 | C3: 1002 | D3: P015 | E3: Tools | F3: South | G3: 10 | H3: 42.01 | I3: 27.04 | J3: 20.44 | K3: =G3*H3 -> 420.1 | L3: =I3*G3 -> 270.4 | M3: =K3-L3 -> 149.7 | N3: =M3/K3*100 -> 35.634373 | O3: =TEXT(A3,"YYYY-MM") -> 2024-11
A4: 45475 | B4: 45475 | C4: 1003 | D4: P026 | E4: Widgets | F4: West | G4: 9 | H4: 101.58 | I4: 69.86 | J4: 115.47 | K4: =G4*H4 -> 914.22 | L4: =I4*G4 -> 628.74 | M4: =K4-L4 -> 285.48 | N4: =M4/K4*100 -> 31.226619 | O4: =TEXT(A4,"YYYY-MM") -> 2024-07
A5: 45315 | B5: 45315 | C5: 1004 | D5: P003 | E5: Gadgets | F5: West | G5: 11 | H5: 29.57 | I5: 17.79 | J5: 140.36 | K5: =G5*H5 -> 325.27 | L5: =I5*G5 -> 195.69 | M5: =K5-L5 -> 129.58 | N5: =M5/K5*100 -> 39.837673 | O5: =TEXT(A5,"YYYY-MM") -> 2024-01
A6: 45328 | B6: 45328 | C6: 1005 | D6: P024 | E6: Gadgets | F6: South | G6: 24 | H6: 95.81 | I6: 30.13 | J6: 63.09 | K6: =G6*H6 -> 2299.44 | L6: =I6*G6 -> 723.12 | M6: =K6-L6 -> 1576.32 | N6: =M6/K6*100 -> 68.552343 | O6: =TEXT(A6,"YYYY-MM") -> 2024-02
A7: 45400 | B7: 45400 | C7: 1006 | D7: P023 | E7: Tools | F7: West | G7: 4 | H7: 38.64 | I7: 16.16 | J7: 116.92 | K7: =G7*H7 -> 154.56 | L7: =I7*G7 -> 64.64 | M7: =K7-L7 -> 89.92 | N7: =M7/K7*100 -> 58.178054 | O7: =TEXT(A7,"YYYY-MM") -> 2024-04
A8: 45496 | B8: 45496 | C8: 1007 | D8: P005 | E8: Accessories | F8: North | G8: 5 | H8: 97.54 | I8: 32.05 | J8: 76.32 | K8: =G8*H8 -> 487.7 | L8: =I8*G8 -> 160.25 | M8: =K8-L8 -> 327.45 | N8: =M8/K8*100 -> 67.141685 | O8: =TEXT(A8,"YYYY-MM") -> 2024-07
A9: 45562 | B9: 45562 | C9: 1008 | D9: P001 | E9: Widgets | F9: East | G9: 10 | H9: 24.05 | I9: 12.13 | J9: 190.76 | K9: =G9*H9 -> 240.5 | L9: =I9*G9 -> 121.3 | M9: =K9-L9 -> 119.2 | N9: =M9/K9*100 -> 49.56341 | O9: =TEXT(A9,"YYYY-MM") -> 2024-09
A10: 45426 | B10: 45426 | C10: 1009 | D10: P017 | E10: Widgets | F10: South | G10: 24 | H10: 29.45 | I10: 21.06 | J10: 183.7 | K10: =G10*H10 -> 706.8 | L10: =I10*G10 -> 505.44 | M10: =K10-L10 -> 201.36 | N10: =M10/K10*100 -> 28.488964 | O10: =TEXT(A10,"YYYY-MM") -> 2024-05
A11: 45542 | B11: 45542 | C11: 1010 | D11: P029 | E11: Tools | F11: North | G11: 15 | H11: 100.13 | I11: 54.04 | J11: 25.15 | K11: =G11*H11 -> 1501.95 | L11: =I11*G11 -> 810.6 | M11: =K11-L11 -> 691.35 | N11: =M11/K11*100 -> 46.030161 | O11: =TEXT(A11,"YYYY-MM") -> 2024-09
A12: 45573 | B12: 45573 | C12: 1011 | D12: P020 | E12: Accessories | F12: South | G12: 12 | H12: 119.48 | I12: 59.4 | J12: 103.52 | K12: =G12*H12 -> 1433.76 | L12: =I12*G12 -> 712.8 | M12: =K12-L12 -> 720.96 | N12: =M12/K12*100 -> 50.284566 | O12: =TEXT(A12,"YYYY-MM") -> 2024-10
A13: 45407 | B13: 45407 | C13: 1012 | D13: P018 | E13: Gadgets | F13: North | G13: 1 | H13: 104.84 | I13: 42.68 | J13: 133.8 | K13: =G13*H13 -> 104.84 | L13: =I13*G13 -> 42.68 | M13: =K13-L13 -> 62.16 | N13: =M13/K13*100 -> 59.290347 | O13: =TEXT(A13,"YYYY-MM") -> 2024-04
... A204: 45381 | B204: 45381 | C204: 1201 | D204: P011 | E204: Accessories | F204: South | G204: 24 | H204: 75.15 | I204: 28.1 | J204: 93.21 | K204: =G204*H204 -> 1803.6 | L204: =I204*G204 -> 674.4 | M204: =K204-L204 -> 1129.2 | N204: =M204/K204*100 -> 62.608117 | O204: =TEXT(A204,"YYYY-MM") -> 2024-03

Sheet KPI_Calc
A1: Total Revenue | B1: =SUM(Data_Cleaned!K2:K204) -> 162332.97
A2: Total Units | B2: =SUM(Data_Cleaned!G2:G204) -> 2565
A3: Total Cost | B3: =SUM(Data_Cleaned!L2:L204) -> 83527.21
A4: Total Gross Profit | B4: =SUM(Data_Cleaned!M2:M204) -> 78805.76
A5: Average margin | B5: =B4/B2 -> 30.723493
A6: Average margin% | B6: =B4/B1*100 -> 48.545751
A18: Region Wise Revenue
A20: Revenue from North region | B20: =SUMIFS(Data_Cleaned!$K$2:$K$204,Data_Cleaned!$F$2:$F$204,"North") -> 43318.38
A21: Revenue from South region | B21: =SUMIFS(Data_Cleaned!$K$2:$K$204,Data_Cleaned!$F$2:$F$204,"South") -> 39250.72
A22: Revenue from East region | B22: =SUMIFS(Data_Cleaned!$K$2:$K$204,Data_Cleaned!$F$2:$F$204,"East") -> 36630.73
A23: Revenue from West region | B23: =SUMIFS(Data_Cleaned!$K$2:$K$204,Data_Cleaned!$F$2:$F$204,"West") -> 43133.14
A24: “The total revenue matches the total revenue by each region.” ✅ | B24: =SUM(B20:B23) -> 162332.97
A47: Monthly Revenue
A49: Month | B49: Revenue | C49: Units | D49: Gross Profit
A50: 2024-01 | B50: =SUMIFS(Data_Cleaned!$K$2:$K$204,Data_Cleaned!$O$2:$O$204,"2024-01") -> 13656.94 | C50: =SUMIFS(Data_Cleaned!G2:$G$204,Data_Cleaned!$O$2:$O$204,"2024-01") -> 214 | D50: =SUMIFS(Data_Cleaned!$M$2:$M$204,Data_Cleaned!$O$2:$O$204,"2024-01") -> 7527.8
A51: 2024-02 | B51: =SUMIFS(Data_Cleaned!$K$2:$K$204,Data_Cleaned!$O$2:$O$204,"2024-02") -> 21072.4 | C51: =SUMIFS(Data_Cleaned!G2:$G$204,Data_Cleaned!$O$2:$O$204,"2024-02") -> 237 | D51: =SUMIFS(Data_Cleaned!$M$2:$M$204,Data_Cleaned!$O$2:$O$204,"2024-02") -> 9935.86
A52: 2024-03 | B52: =SUMIFS(Data_Cleaned!$K$2:$K$204,Data_Cleaned!$O$2:$O$204,"2024-03") -> 14263.05 | C52: =SUMIFS(Data_Cleaned!G2:$G$204,Data_Cleaned!$O$2:$O$204,"2024-03") -> 247 | D52: =SUMIFS(Data_Cleaned!$M$2:$M$204,Data_Cleaned!$O$2:$O$204,"2024-03") -> 6823.05
A53: 2024-04 | B53: =SUMIFS(Data_Cleaned!$K$2:$K$204,Data_Cleaned!$O$2:$O$204,"2024-04") -> 6762.45 | C53: =SUMIFS(Data_Cleaned!G2:$G$204,Data_Cleaned!$O$2:$O$204,"2024-04") -> 111 | D53: =SUMIFS(Data_Cleaned!$M$2:$M$204,Data_Cleaned!$O$2:$O$204,"2024-04") -> 3124.03
A54: 2024-05 | B54: =SUMIFS(Data_Cleaned!$K$2:$K$204,Data_Cleaned!$O$2:$O$204,"2024-05") -> 15367.54 | C54: =SUMIFS(Data_Cleaned!G2:$G$204,Data_Cleaned!$O$2:$O$204,"2024-05") -> 248 | D54: =SUMIFS(Data_Cleaned!$M$2:$M$204,Data_Cleaned!$O$2:$O$204,"2024-05") -> 7822.45
A55: 2024-06 | B55: =SUMIFS(Data_Cleaned!$K$2:$K$204,Data_Cleaned!$O$2:$O$204,"2024-06") -> 12866.31 | C55: =SUMIFS(Data_Cleaned!G2:$G$204,Data_Cleaned!$O$2:$O$204,"2024-06") -> 205 | D55: =SUMIFS(Data_Cleaned!$M$2:$M$204,Data_Cleaned!$O$2:$O$204,"2024-06") -> 5970.21
A56: 2024-07 | B56: =SUMIFS(Data_Cleaned!$K$2:$K$204,Data_Cleaned!$O$2:$O$204,"2024-07") -> 13237.96 | C56: =SUMIFS(Data_Cleaned!G2:$G$204,Data_Cleaned!$O$2:$O$204,"2024-07") -> 262 | D56: =SUMIFS(Data_Cleaned!$M$2:$M$204,Data_Cleaned!$O$2:$O$204,"2024-07") -> 6285.75
A57: 2024-08 | B57: =SUMIFS(Data_Cleaned!$K$2:$K$204,Data_Cleaned!$O$2:$O$204,"2024-08") -> 25642.76 | C57: =SUMIFS(Data_Cleaned!G2:$G$204,Data_Cleaned!$O$2:$O$204,"2024-08") -> 353 | D57: =SUMIFS(Data_Cleaned!$M$2:$M$204,Data_Cleaned!$O$2:$O$204,"2024-08") -> 12151.83
A58: 2024-09 | B58: =SUMIFS(Data_Cleaned!$K$2:$K$204,Data_Cleaned!$O$2:$O$204,"2024-09") -> 11124.54 | C58: =SUMIFS(Data_Cleaned!G2:$G$204,Data_Cleaned!$O$2:$O$204,"2024-09") -> 225 | D58: =SUMIFS(Data_Cleaned!$M$2:$M$204,Data_Cleaned!$O$2:$O$204,"2024-09") -> 4941.9
A59: 2024-10 | B59: =SUMIFS(Data_Cleaned!$K$2:$K$204,Data_Cleaned!$O$2:$O$204,"2024-10") -> 11941.62 | C59: =SUMIFS(Data_Cleaned!G2:$G$204,Data_Cleaned!$O$2:$O$204,"2024-10") -> 166 | D59: =SUMIFS(Data_Cleaned!$M$2:$M$204,Data_Cleaned!$O$2:$O$204,"2024-10") -> 5850.96
A60: 2024-11 | B60: =SUMIFS(Data_Cleaned!$K$2:$K$204,Data_Cleaned!$O$2:$O$204,"2024-11") -> 13166.92 | C60: =SUMIFS(Data_Cleaned!G2:$G$204,Data_Cleaned!$O$2:$O$204,"2024-11") -> 245 | D60: =SUMIFS(Data_Cleaned!$M$2:$M$204,Data_Cleaned!$O$2:$O$204,"2024-11") -> 6556.59
A61: 2024-12 | B61: =SUMIFS(Data_Cleaned!$K$2:$K$204,Data_Cleaned!$O$2:$O$204,"2024-12") -> 3230.48 | C61: =SUMIFS(Data_Cleaned!G2:$G$204,Data_Cleaned!$O$2:$O$204,"2024-12") -> 52 | D61: =SUMIFS(Data_Cleaned!$M$2:$M$204,Data_Cleaned!$O$2:$O$204,"2024-12") -> 1815.33
A62: All the data matches correctly✅ | B62: =SUM(B50:B61) -> 162332.97 | C62: =SUM(C50:C61) -> 2565 | D62: =SUM(D50:D61) -> 78805.76
A74: Product Wise Analysis
A75: Product line | B75: Total
A76: Gadgets | B76: =SUMIFS(Data_Cleaned!$K$2:$K$204,Data_Cleaned!$E$2:$E$204,"Gadgets") -> 42009.9
A77: Tools | B77: =SUMIFS(Data_Cleaned!$K$2:$K$204,Data_Cleaned!$E$2:$E$204,"Tools") -> 49824.98 | D77: =D57/D62 -> 0.15419977 | E77: =1-D77 -> 0.84580023
A78: Widgets | B78: =SUMIFS(Data_Cleaned!$K$2:$K$204,Data_Cleaned!$E$2:$E$204,"widgets") -> 29784.7
A79: Accessories | B79: =SUMIFS(Data_Cleaned!$K$2:$K$204,Data_Cleaned!$E$2:$E$204,"Accessories") -> 40713.39
A80: Total | B80: =SUBTOTAL(109,Table4[Total]) -> 162332.97
A86: Tools | B86: =B77/B80 -> 0.30693075 | C86: =1-B86 -> 0.69306925
B89: =B20/B24 -> 0.26684893 | C89: =1-B89 -> 0.73315107

Sheet Assumptions
A1: Description | B1: Parameter | C1: Value
A2: Price % change | B2: PriceChange% | C2: 0
A3: Cost % change | B3: CostInflation% | C3: 0
A4: Marketing budget % change | B4: MarketingChange% | C4: 0
A5: Number of months to forecast | B5: ForecastMonths | C5: 12
A6: Selected scenario name | B6: ScenarioSelect | C6: Base

Sheet Scenario_Model
A1: Month | B1: Revenue | C1: Units | D1: Gross Profit | E1: BaseUnitPrice | F1: BaseUnitCost | G1: ProjectedUnitPrice | H1: ProjectedUnitCost | I1: ProjectedUnits | J1: ProjectedRevenue | K1: ProjectedGrossProfit
A2: 2024-01 | B2: =SUMIFS(Data_Cleaned!$K$2:$K$204,Data_Cleaned!$O$2:$O$204,"2024-01") -> 13656.94 | C2: 214 | D2: =SUMIFS(Data_Cleaned!$M$2:$M$204,Data_Cleaned!$O$2:$O$204,"2024-01") -> 7527.8 | E2: =B2/C2 -> 63.817477 | F2: =(B2-D2)/C2 -> 28.640841 | G2: =E2*(1+Assumptions!$C$2) -> 63.817477 | H2: =F2*(1+Assumptions!$C$3) -> 28.640841 | I2: =C2*(1+Assumptions!$C$4) -> 214 | J2: =G2*I2 -> 13656.94 | K2: =J2-(H2*I2) -> 7527.8
A3: 2024-02 | B3: =SUMIFS(Data_Cleaned!$K$2:$K$204,Data_Cleaned!$O$2:$O$204,"2024-02") -> 21072.4 | C3: 237 | D3: =SUMIFS(Data_Cleaned!$M$2:$M$204,Data_Cleaned!$O$2:$O$204,"2024-02") -> 9935.86 | E3: =B3/C3 -> 88.91308 | F3: =(B3-D3)/C3 -> 46.98962 | G3: =E3*(1+Assumptions!$C$2) -> 88.91308 | H3: =F3*(1+Assumptions!$C$3) -> 46.98962 | I3: =C3*(1+Assumptions!$C$4) -> 237 | J3: =G3*I3 -> 21072.4 | K3: =J3-(H3*I3) -> 9935.86
A4: 2024-03 | B4: =SUMIFS(Data_Cleaned!$K$2:$K$204,Data_Cleaned!$O$2:$O$204,"2024-03") -> 14263.05 | C4: 247 | D4: =SUMIFS(Data_Cleaned!$M$2:$M$204,Data_Cleaned!$O$2:$O$204,"2024-03") -> 6823.05 | E4: =B4/C4 -> 57.745142 | F4: =(B4-D4)/C4 -> 30.121457 | G4: =E4*(1+Assumptions!$C$2) -> 57.745142 | H4: =F4*(1+Assumptions!$C$3) -> 30.121457 | I4: =C4*(1+Assumptions!$C$4) -> 247 | J4: =G4*I4 -> 14263.05 | K4: =J4-(H4*I4) -> 6823.05
A5: 2024-04 | B5: =SUMIFS(Data_Cleaned!$K$2:$K$204,Data_Cleaned!$O$2:$O$204,"2024-04") -> 6762.45 | C5: 111 | D5: =SUMIFS(Data_Cleaned!$M$2:$M$204,Data_Cleaned!$O$2:$O$204,"2024-04") -> 3124.03 | E5: =B5/C5 -> 60.922973 | F5: =(B5-D5)/C5 -> 32.778559 | G5: =E5*(1+Assumptions!$C$2) -> 60.922973 | H5: =F5*(1+Assumptions!$C$3) -> 32.778559 | I5: =C5*(1+Assumptions!$C$4) -> 111 | J5: =G5*I5 -> 6762.45 | K5: =J5-(H5*I5) -> 3124.03
A6: 2024-05 | B6: =SUMIFS(Data_Cleaned!$K$2:$K$204,Data_Cleaned!$O$2:$O$204,"2024-05") -> 15367.54 | C6: 248 | D6: =SUMIFS(Data_Cleaned!$M$2:$M$204,Data_Cleaned!$O$2:$O$204,"2024-05") -> 7822.45 | E6: =B6/C6 -> 61.965887 | F6: =(B6-D6)/C6 -> 30.42375 | G6: =E6*(1+Assumptions!$C$2) -> 61.965887 | H6: =F6*(1+Assumptions!$C$3) -> 30.42375 | I6: =C6*(1+Assumptions!$C$4) -> 248 | J6: =G6*I6 -> 15367.54 | K6: =J6-(H6*I6) -> 7822.45
A7: 2024-06 | B7: =SUMIFS(Data_Cleaned!$K$2:$K$204,Data_Cleaned!$O$2:$O$204,"2024-06") -> 12866.31 | C7: 205 | D7: =SUMIFS(Data_Cleaned!$M$2:$M$204,Data_Cleaned!$O$2:$O$204,"2024-06") -> 5970.21 | E7: =B7/C7 -> 62.762488 | F7: =(B7-D7)/C7 -> 33.639512 | G7: =E7*(1+Assumptions!$C$2) -> 62.762488 | H7: =F7*(1+Assumptions!$C$3) -> 33.639512 | I7: =C7*(1+Assumptions!$C$4) -> 205 | J7: =G7*I7 -> 12866.31 | K7: =J7-(H7*I7) -> 5970.21
A8: 2024-07 | B8: =SUMIFS(Data_Cleaned!$K$2:$K$204,Data_Cleaned!$O$2:$O$204,"2024-07") -> 13237.96 | C8: 262 | D8: =SUMIFS(Data_Cleaned!$M$2:$M$204,Data_Cleaned!$O$2:$O$204,"2024-07") -> 6285.75 | E8: =B8/C8 -> 50.526565 | F8: =(B8-D8)/C8 -> 26.535153 | G8: =E8*(1+Assumptions!$C$2) -> 50.526565 | H8: =F8*(1+Assumptions!$C$3) -> 26.535153 | I8: =C8*(1+Assumptions!$C$4) -> 262 | J8: =G8*I8 -> 13237.96 | K8: =J8-(H8*I8) -> 6285.75
A9: 2024-08 | B9: =SUMIFS(Data_Cleaned!$K$2:$K$204,Data_Cleaned!$O$2:$O$204,"2024-08") -> 25642.76 | C9: 353 | D9: =SUMIFS(Data_Cleaned!$M$2:$M$204,Data_Cleaned!$O$2:$O$204,"2024-08") -> 12151.83 | E9: =B9/C9 -> 72.64238 | F9: =(B9-D9)/C9 -> 38.217932 | G9: =E9*(1+Assumptions!$C$2) -> 72.64238 | H9: =F9*(1+Assumptions!$C$3) -> 38.217932 | I9: =C9*(1+Assumptions!$C$4) -> 353 | J9: =G9*I9 -> 25642.76 | K9: =J9-(H9*I9) -> 12151.83
A10: 2024-09 | B10: =SUMIFS(Data_Cleaned!$K$2:$K$204,Data_Cleaned!$O$2:$O$204,"2024-09") -> 11124.54 | C10: 225 | D10: =SUMIFS(Data_Cleaned!$M$2:$M$204,Data_Cleaned!$O$2:$O$204,"2024-09") -> 4941.9 | E10: =B10/C10 -> 49.4424 | F10: =(B10-D10)/C10 -> 27.4784 | G10: =E10*(1+Assumptions!$C$2) -> 49.4424 | H10: =F10*(1+Assumptions!$C$3) -> 27.4784 | I10: =C10*(1+Assumptions!$C$4) -> 225 | J10: =G10*I10 -> 11124.54 | K10: =J10-(H10*I10) -> 4941.9
A11: 2024-10 | B11: =SUMIFS(Data_Cleaned!$K$2:$K$204,Data_Cleaned!$O$2:$O$204,"2024-10") -> 11941.62 | C11: 166 | D11: =SUMIFS(Data_Cleaned!$M$2:$M$204,Data_Cleaned!$O$2:$O$204,"2024-10") -> 5850.96 | E11: =B11/C11 -> 71.93747 | F11: =(B11-D11)/C11 -> 36.690723 | G11: =E11*(1+Assumptions!$C$2) -> 71.93747 | H11: =F11*(1+Assumptions!$C$3) -> 36.690723 | I11: =C11*(1+Assumptions!$C$4) -> 166 | J11: =G11*I11 -> 11941.62 | K11: =J11-(H11*I11) -> 5850.96
A12: 2024-11 | B12: =SUMIFS(Data_Cleaned!$K$2:$K$204,Data_Cleaned!$O$2:$O$204,"2024-11") -> 13166.92 | C12: 245 | D12: =SUMIFS(Data_Cleaned!$M$2:$M$204,Data_Cleaned!$O$2:$O$204,"2024-11") -> 6556.59 | E12: =B12/C12 -> 53.742531 | F12: =(B12-D12)/C12 -> 26.980939 | G12: =E12*(1+Assumptions!$C$2) -> 53.742531 | H12: =F12*(1+Assumptions!$C$3) -> 26.980939 | I12: =C12*(1+Assumptions!$C$4) -> 245 | J12: =G12*I12 -> 13166.92 | K12: =J12-(H12*I12) -> 6556.59
A13: 2024-12 | B13: =SUMIFS(Data_Cleaned!$K$2:$K$204,Data_Cleaned!$O$2:$O$204,"2024-12") -> 3230.48 | C13: 52 | D13: =SUMIFS(Data_Cleaned!$M$2:$M$204,Data_Cleaned!$O$2:$O$204,"2024-12") -> 1815.33 | E13: =B13/C13 -> 62.124615 | F13: =(B13-D13)/C13 -> 27.214423 | G13: =E13*(1+Assumptions!$C$2) -> 62.124615 | H13: =F13*(1+Assumptions!$C$3) -> 27.214423 | I13: =C13*(1+Assumptions!$C$4) -> 52 | J13: =G13*I13 -> 3230.48 | K13: =J13-(H13*I13) -> 1815.33

Sheet Slicers
A1: Region | B1: ProductLine | C1: COGS | D1: Revenue | E1: Gross_profit | F1: UnitsSold | G1: Helper
A2: North | B2: Gadgets | C2: 8.03 | D2: 15.22 | E2: 7.19 | F2: 1 | G2: 2024-11
A3: South | B3: Tools | C3: 270.4 | D3: 420.1 | E3: 149.7 | F3: 10 | G3: 2024-11
A4: West | B4: Widgets | C4: 628.74 | D4: 914.22 | E4: 285.48 | F4: 9 | G4: 2024-07
A5: West | B5: Gadgets | C5: 195.69 | D5: 325.27 | E5: 129.58 | F5: 11 | G5: 2024-01
A6: South | B6: Gadgets | C6: 723.12 | D6: 2299.44 | E6: 1576.32 | F6: 24 | G6: 2024-02
A7: West | B7: Tools | C7: 64.64 | D7: 154.56 | E7: 89.92 | F7: 4 | G7: 2024-04
A8: North | B8: Accessories | C8: 160.25 | D8: 487.7 | E8: 327.45 | F8: 5 | G8: 2024-07
A9: East | B9: Widgets | C9: 121.3 | D9: 240.5 | E9: 119.2 | F9: 10 | G9: 2024-09
A10: South | B10: Widgets | C10: 505.44 | D10: 706.8 | E10: 201.36 | F10: 24 | G10: 2024-05
A11: North | B11: Tools | C11: 810.6 | D11: 1501.95 | E11: 691.35 | F11: 15 | G11: 2024-09
A12: South | B12: Accessories | C12: 712.8 | D12: 1433.76 | E12: 720.96 | F12: 12 | G12: 2024-10
A13: North | B13: Gadgets | C13: 42.68 | D13: 104.84 | E13: 62.16 | F13: 1 | G13: 2024-04
... A204: South | B204: Accessories | C204: 674.4 | D204: 1803.6 | E204: 1129.2 | F204: 24 | G204: 2024-03

Sheet Product Table
A1: ProductID | B1: ProductLine | C1: UnitCost | D1: UnitPrice | E1: OrderID | F1: date
A2: P001 | B2: Widgets | C2: 12.13 | D2: 24.05 | E2: =_xlfn.XLOOKUP(A2,Data_Cleaned!D:D,Data_Cleaned!C:C) -> 1008 | F2: =_xlfn.XLOOKUP(A2,Data_Cleaned!D:D,Data_Cleaned!A:A) -> 45562
A3: P001 | B3: Accessories | C3: 31.15 | D3: 79.54 | E3: =_xlfn.XLOOKUP(A3,Data_Cleaned!D:D,Data_Cleaned!C:C) -> 1008 | F3: =_xlfn.XLOOKUP(A3,Data_Cleaned!D:D,Data_Cleaned!A:A) -> 45562
A4: P001 | B4: Gadgets | C4: 12.73 | D4: 36.27 | E4: =_xlfn.XLOOKUP(A4,Data_Cleaned!D:D,Data_Cleaned!C:C) -> 1008 | F4: =_xlfn.XLOOKUP(A4,Data_Cleaned!D:D,Data_Cleaned!A:A) -> 45562
A5: P001 | B5: Tools | C5: 53.31 | D5: 110.21 | E5: =_xlfn.XLOOKUP(A5,Data_Cleaned!D:D,Data_Cleaned!C:C) -> 1008 | F5: =_xlfn.XLOOKUP(A5,Data_Cleaned!D:D,Data_Cleaned!A:A) -> 45562
A6: P001 | B6: Gadgets | C6: 40.12 | D6: 93.64 | E6: =_xlfn.XLOOKUP(A6,Data_Cleaned!D:D,Data_Cleaned!C:C) -> 1008 | F6: =_xlfn.XLOOKUP(A6,Data_Cleaned!D:D,Data_Cleaned!A:A) -> 45562
A7: P001 | B7: Tools | C7: 35.03 | D7: 58.64 | E7: =_xlfn.XLOOKUP(A7,Data_Cleaned!D:D,Data_Cleaned!C:C) -> 1008 | F7: =_xlfn.XLOOKUP(A7,Data_Cleaned!D:D,Data_Cleaned!A:A) -> 45562
A8: P001 | B8: Tools | C8: 22.82 | D8: 30.66 | E8: =_xlfn.XLOOKUP(A8,Data_Cleaned!D:D,Data_Cleaned!C:C) -> 1008 | F8: =_xlfn.XLOOKUP(A8,Data_Cleaned!D:D,Data_Cleaned!A:A) -> 45562
A9: P002 | B9: accessories | C9: 66.45 | D9: 114.48 | E9: =_xlfn.XLOOKUP(A9,Data_Cleaned!D:D,Data_Cleaned!C:C) -> 1027 | F9: =_xlfn.XLOOKUP(A9,Data_Cleaned!D:D,Data_Cleaned!A:A) -> 45445
A10: P002 | B10: Gadgets | C10: 64.98 | D10: 111.78 | E10: =_xlfn.XLOOKUP(A10,Data_Cleaned!D:D,Data_Cleaned!C:C) -> 1027 | F10: =_xlfn.XLOOKUP(A10,Data_Cleaned!D:D,Data_Cleaned!A:A) -> 45445
A11: P002 | B11: Tools | C11: 36.02 | D11: 58.04 | E11: =_xlfn.XLOOKUP(A11,Data_Cleaned!D:D,Data_Cleaned!C:C) -> 1027 | F11: =_xlfn.XLOOKUP(A11,Data_Cleaned!D:D,Data_Cleaned!A:A) -> 45445
A12: P002 | B12: Widgets | C12: 14.58 | D12: 41.5 | E12: =_xlfn.XLOOKUP(A12,Data_Cleaned!D:D,Data_Cleaned!C:C) -> 1027 | F12: =_xlfn.XLOOKUP(A12,Data_Cleaned!D:D,Data_Cleaned!A:A) -> 45445
A13: P002 | B13: Gadgets | C13: 40.82 | D13: 94.87 | E13: =_xlfn.XLOOKUP(A13,Data_Cleaned!D:D,Data_Cleaned!C:C) -> 1027 | F13: =_xlfn.XLOOKUP(A13,Data_Cleaned!D:D,Data_Cleaned!A:A) -> 45445
... A204: P030 | B204: Widgets | C204: 40 | D204: 52.49 | E204: =_xlfn.XLOOKUP(A204,Data_Cleaned!D:D,Data_Cleaned!C:C) -> 1092 | F204: =_xlfn.XLOOKUP(A204,Data_Cleaned!D:D,Data_Cleaned!A:A) -> 45561

Sheet Pivot tables
B3: ProductLine | C3: Values
B4: Accessories | D4: Gadgets | F4: Tools | H4: Widgets | J4: Total Sum of Revenue | K4: Total Sum of UnitsSold
A5: Region | B5: Sum of Revenue | C5: Sum of UnitsSold | D5: Sum of Revenue | E5: Sum of UnitsSold | F5: Sum of Revenue | G5: Sum of UnitsSold | H5: Sum of Revenue | I5: Sum of UnitsSold
A6: East | B6: 10467.39 | C6: 142 | D6: 9470.12 | E6: 192 | F6: 10068.47 | G6: 161 | H6: 6624.75 | I6: 109 | J6: 36630.73 | K6: 604
A7: North | B7: 8785.72 | C7: 123 | D7: 12253.76 | E7: 194 | F7: 15439.58 | G7: 211 | H7: 6839.32 | I7: 131 | J7: 43318.38 | K7: 659
A8: South | B8: 14010.74 | C8: 220 | D8: 10745.23 | E8: 137 | F8: 9257.91 | G8: 167 | H8: 5236.84 | I8: 98 | J8: 39250.72 | K8: 622
A9: West | B9: 7449.54 | C9: 111 | D9: 9540.79 | E9: 142 | F9: 15059.02 | G9: 245 | H9: 11083.79 | I9: 182 | J9: 43133.14 | K9: 680
A10: Grand Total | B10: 40713.39 | C10: 596 | D10: 42009.9 | E10: 665 | F10: 49824.98 | G10: 784 | H10: 29784.7 | I10: 520 | J10: 162332.97 | K10: 2565
A34: Helper | B34: Sum of Revenue | C34: Sum of Gross_profit
A35: 2024-01 | B35: 13656.94 | C35: 7527.8
A36: 2024-02 | B36: 21072.4 | C36: 9935.86
A37: 2024-03 | B37: 14263.05 | C37: 6823.05
A38: 2024-04 | B38: 6762.45 | C38: 3124.03
A39: 2024-05 | B39: 15367.54 | C39: 7822.45
A40: 2024-06 | B40: 12866.31 | C40: 5970.21
A41: 2024-07 | B41: 13237.96 | C41: 6285.75
A42: 2024-08 | B42: 25642.76 | C42: 12151.83
A43: 2024-09 | B43: 11124.54 | C43: 4941.9
A44: 2024-10 | B44: 11941.62 | C44: 5850.96
A45: 2024-11 | B45: 13166.92 | C45: 6556.59
A46: 2024-12 | B46: 3230.48 | C46: 1815.33
A47: Grand Total | B47: 162332.97 | C47: 78805.76
A60: ProductLine | B60: Sum of Revenue | C60: Sum of COGS | D60: Sum of Gross_profit
A61: Accessories | B61: 40713.39 | C61: 20703.48 | D61: 20009.91
A62: Gadgets | B62: 42009.9 | C62: 20644.86 | D62: 21365.04
A63: Tools | B63: 49824.98 | C63: 26249.11 | D63: 23575.87
A64: Widgets | B64: 29784.7 | C64: 15929.76 | D64: 13854.94
A65: Grand Total | B65: 162332.97 | C65: 83527.21 | D65: 78805.76
C80: Helper | D80: Values
C81: 2024-01 | E81: 2024-02 | G81: 2024-03 | I81: 2024-04 | K81: 2024-05 | M81: 2024-06 | O81: 2024-07 | Q81: 2024-08 | S81: 2024-09 | U81: 2024-10 | W81: 2024-11 | Y81: 2024-12 | AA81: Total Sum of Revenue | AB81: Total Sum of UnitsSold
A82: Region | B82: ProductLine | C82: Sum of Revenue | D82: Sum of UnitsSold | E82: Sum of Revenue | F82: Sum of UnitsSold | G82: Sum of Revenue | H82: Sum of UnitsSold | I82: Sum of Revenue | J82: Sum of UnitsSold | K82: Sum of Revenue | L82: Sum of UnitsSold | M82: Sum of Revenue | N82: Sum of UnitsSold | O82: Sum of Revenue | P82: Sum of UnitsSold | Q82: Sum of Revenue | R82: Sum of UnitsSold | S82: Sum of Revenue | T82: Sum of UnitsSold | U82: Sum of Revenue | V82: Sum of UnitsSold | W82: Sum of Revenue | X82: Sum of UnitsSold | Y82: Sum of Revenue | Z82: Sum of UnitsSold
A83: East | C83: 1834.02 | D83: 32 | E83: 10428.06 | F83: 118 | G83: 5600.21 | H83: 94 | I83: 406.27 | J83: 13 | K83: 3014.69 | L83: 39 | M83: 1126.72 | N83: 21 | O83: 1890.33 | P83: 55 | Q83: 5014.39 | R83: 89 | S83: 666.96 | T83: 30 | U83: 2297.32 | V83: 38 | W83: 4351.76 | X83: 75 | AA83: 36630.73 | AB83: 604
B84: Accessories | C84: 94.84 | D84: 2 | E84: 4818.66 | F84: 47 | G84: 1966.96 | H84: 23 | I84: 185.79 | J84: 11 | K84: 1042.61 | L84: 17 | M84: 401.38 | N84: 7 | S84: 147.46 | T84: 2 | U84: 504.6 | V84: 12 | W84: 1305.09 | X84: 21 | AA84: 10467.39 | AB84: 142
B85: Gadgets | E85: 3755.62 | F85: 49 | G85: 1995.95 | H85: 50 | K85: 1972.08 | L85: 22 | O85: 318.78 | P85: 14 | Q85: 814.66 | R85: 32 | W85: 613.03 | X85: 25 | AA85: 9470.12 | AB85: 192
B86: Tools | C86: 313.56 | D86: 12 | E86: 1748.8 | F86: 20 | M86: 725.34 | N86: 14 | O86: 1571.55 | P86: 41 | Q86: 3916.5 | R86: 48 | U86: 1792.72 | V86: 26 | AA86: 10068.47 | AB86: 161
B87: Widgets | C87: 1425.62 | D87: 18 | E87: 104.98 | F87: 2 | G87: 1637.3 | H87: 21 | I87: 220.48 | J87: 2 | M87: 0 | N87: 0 | Q87: 283.23 | R87: 9 | S87: 519.5 | T87: 28 | W87: 2433.64 | X87: 29 | AA87: 6624.75 | AB87: 109
A88: North | C88: 2447.84 | D88: 56 | E88: 1321.54 | F88: 22 | G88: 1816.67 | H88: 31 | I88: 2063.84 | J88: 24 | K88: 2359.04 | L88: 44 | M88: 4992.18 | N88: 81 | O88: 3168.21 | P88: 53 | Q88: 8075.59 | R88: 92 | S88: 7649.73 | T88: 131 | U88: 4019.17 | V88: 49 | W88: 2634.34 | X88: 49 | Y88: 2770.23 | Z88: 27 | AA88: 43318.38 | AB88: 659
B89: Accessories | E89: 1321.54 | F89: 22 | K89: 36.81 | L89: 1 | M89: 237 | N89: 2 | O89: 1663.7 | P89: 30 | Q89: 5077.39 | R89: 52 | S89: 449.28 | T89: 16 | AA89: 8785.72 | AB89: 123
B90: Gadgets | I90: 104.84 | J90: 1 | K90: 2322.23 | L90: 43 | M90: 3090.58 | N90: 51 | O90: 1504.51 | P90: 23 | Q90: 1880.8 | R90: 20 | S90: 2383.26 | T90: 39 | U90: 383.1 | V90: 10 | W90: 15.22 | X90: 1 | Y90: 569.22 | Z90: 6 | AA90: 12253.76 | AB90: 194
B91: Tools | C91: 195.8 | D91: 11 | G91: 1320.41 | H91: 13 | I91: 1180.92 | J91: 13 | M91: 536.76 | N91: 14 | Q91: 1117.4 | R91: 20 | S91: 3335.53 | T91: 56 | U91: 3636.07 | V91: 39 | W91: 1915.68 | X91: 24 | Y91: 2201.01 | Z91: 21 | AA91: 15439.58 | AB91: 211
B92: Widgets | C92: 2252.04 | D92: 45 | G92: 496.26 | H92: 18 | I92: 778.08 | J92: 10 | M92: 1127.84 | N92: 14 | S92: 1481.66 | T92: 20 | W92: 703.44 | X92: 24 | AA92: 6839.32 | AB92: 131
A93: South | C93: 2351.17 | D93: 40 | E93: 4604.4 | F93: 45 | G93: 3362.85 | H93: 62 | I93: 1986.2 | J93: 33 | K93: 6576.38 | L93: 102 | M93: 1351.8 | N93: 33 | O93: 3146.76 | P93: 54 | Q93: 6328.85 | R93: 86 | S93: 1799.45 | T93: 35 | U93: 2372.79 | V93: 35 | W93: 4909.82 | X93: 72 | Y93: 460.25 | Z93: 25 | AA93: 39250.72 | AB93: 622
B94: Accessories | C94: 1021.8 | D94: 12 | G94: 2057.07 | H94: 41 | I94: 881.6 | J94: 19 | K94: 2185.48 | L94: 22 | M94: 228.96 | N94: 2 | O94: 422 | P94: 20 | Q94: 4269.26 | R94: 43 | S94: 516.25 | T94: 7 | U94: 1968.07 | V94: 29 | Y94: 460.25 | Z94: 25 | AA94: 14010.74 | AB94: 220
B95: Gadgets | E95: 4604.4 | F95: 45 | G95: 1305.78 | H95: 21 | I95: 1104.6 | J95: 14 | K95: 2751.78 | L95: 36 | M95: 189.54 | N95: 13 | U95: 169.84 | V95: 2 | W95: 619.29 | X95: 6 | AA95: 10745.23 | AB95: 137
B96: Tools | C96: 505.36 | D96: 17 | G96: 0 | H96: 0 | O96: 1764.91 | P96: 19 | Q96: 1392.95 | R96: 35 | S96: 1283.2 | T96: 28 | U96: 234.88 | V96: 4 | W96: 4076.61 | X96: 64 | AA96: 9257.91 | AB96: 167
B97: Widgets | C97: 824.01 | D97: 11 | K97: 1639.12 | L97: 44 | M97: 933.3 | N97: 18 | O97: 959.85 | P97: 15 | Q97: 666.64 | R97: 8 | W97: 213.92 | X97: 2 | AA97: 5236.84 | AB97: 98
A98: West | C98: 7023.91 | D98: 86 | E98: 4718.4 | F98: 52 | G98: 3483.32 | H98: 60 | I98: 2306.14 | J98: 41 | K98: 3417.43 | L98: 63 | M98: 5395.61 | N98: 70 | O98: 5032.66 | P98: 100 | Q98: 6223.93 | R98: 86 | S98: 1008.4 | T98: 29 | U98: 3252.34 | V98: 44 | W98: 1271 | X98: 49 | AA98: 43133.14 | AB98: 680
B99: Accessories | C99: 0 | D99: 0 | E99: 2914.75 | F99: 25 | G99: 718.78 | H99: 18 | I99: 146.12 | J99: 2 | K99: 1349.81 | L99: 31 | O99: 741.76 | P99: 19 | Q99: 1512.68 | R99: 13 | S99: 65.64 | T99: 3 | AA99: 7449.54 | AB99: 111
B100: Gadgets | C100: 2284.87 | D100: 35 | E100: 636.94 | F100: 10 | I100: 118.84 | J100: 2 | K100: 96.65 | L100: 1 | M100: 2179.53 | N100: 24 | Q100: 3292 | R100: 59 | U100: 931.96 | V100: 11 | AA100: 9540.79 | AB100: 142
B101: Tools | C101: 4739.04 | D101: 51 | G101: 469.54 | H101: 17 | I101: 1196.06 | J101: 29 | K101: 1520.97 | L101: 25 | M101: 1491.63 | N101: 21 | O101: 2716.81 | P101: 49 | U101: 2281.11 | V101: 32 | W101: 643.86 | X101: 21 | AA101: 15059.02 | AB101: 245
B102: Widgets | E102: 1166.71 | F102: 17 | G102: 2295 | H102: 25 | I102: 845.12 | J102: 8 | K102: 450 | L102: 6 | M102: 1724.45 | N102: 25 | O102: 1574.09 | P102: 32 | Q102: 1419.25 | R102: 14 | S102: 942.76 | T102: 26 | U102: 39.27 | V102: 1 | W102: 627.14 | X102: 28 | AA102: 11083.79 | AB102: 182
A103: Grand Total | C103: 13656.94 | D103: 214 | E103: 21072.4 | F103: 237 | G103: 14263.05 | H103: 247 | I103: 6762.45 | J103: 111 | K103: 15367.54 | L103: 248 | M103: 12866.31 | N103: 205 | O103: 13237.96 | P103: 262 | Q103: 25642.76 | R103: 353 | S103: 11124.54 | T103: 225 | U103: 11941.62 | V103: 166 | W103: 13166.92 | X103: 245 | Y103: 3230.48 | Z103: 52 | AA103: 162332.97 | AB103: 2565

Sheet Dashboard
A12: =KPI_Calc!B86 -> 0.30693075
A17: =KPI_Calc!B89 -> 0.26684893
K18: z
A19: =KPI_Calc!D77 -> 0.15419977
